jdk/__init__.py
jdk/client/__init__.py
jdk/client/adoptium.py
jdk/client/client.py
jdk/client/corretto.py
jdk/client/zulu.py
jdk/enums.py
jdk/extension.py
jdk/extractor.py
install_jdk-1.0.1.dist-info/LICENSE.md
install_jdk-1.0.1.dist-info/METADATA
install_jdk-1.0.1.dist-info/WHEEL
install_jdk-1.0.1.dist-info/RECORD
