Metadata-Version: 2.1
Name: install-jdk
Version: 1.0.1
Summary: install-jdk allows you to easily install latest Java OpenJDK version. Supports OpenJDK builds from Adoptium (previously AdoptOpenJDK), Corretto, and Zulu. Simplify your Java development with the latest OpenJDK builds.
Home-page: https://github.com/jyksnw/install-jdk
License: MIT
Keywords: Java,OpenJDK,AdoptOpenJDK,Adoptium,Corretto,Zulu,JDK,JRE
Author: Jason Snow
Author-email: jason.snow@outlook.com
Requires-Python: >=3.8.1,<4.0.0
Classifier: Development Status :: 5 - Production/Stable
Classifier: Intended Audience :: Developers
Classifier: License :: OSI Approved :: MIT License
Classifier: Operating System :: OS Independent
Classifier: Programming Language :: Python :: 3
Classifier: Programming Language :: Python :: 3.9
Classifier: Programming Language :: Python :: 3.10
Classifier: Programming Language :: Python :: 3.11
Classifier: Programming Language :: Python :: 3
Classifier: Topic :: Software Development
Classifier: Topic :: Utilities
Project-URL: Changelog, https://github.com/jyksnw/install-jdk/releases
Project-URL: Documentation, https://github.com/jyksnw/install-jdk
Project-URL: Repository, https://github.com/jyksnw/install-jdk
